{"cameraMode":{"drawMode":0,"name":"Shaded","section":"Shading Mode"},"sceneLighting":true,"audioPlay":false,"sceneViewState":{"showFog":true,"showMaterialUpdate":false,"showSkybox":true,"showFlares":true,"showImageEffects":true,"showParticleSystems":true,"showVisualEffectGraphs":true,"m_FxEnabled":true},"in2DMode":false,"pivot":{"x":-136.3500518798828,"y":112.43443298339844,"z":642.6907348632813},"rotation":{"x":-0.0864604189991951,"y":0.22202126681804658,"z":0.016925111413002015,"w":0.9709553718566895},"size":4.961187362670898,"orthographic":false}